DocumentsClassifier/Document_Classifier.py
DocumentsClassifier/__init__.py
DocumentsClassifier/classification.py
DocumentsClassifier/config.yml
DocumentsClassifier/embeddings.py
DocumentsClassifier/utils.py
Documents_Classifier-0.0.3.dist-info/LICENSE
Documents_Classifier-0.0.3.dist-info/METADATA
Documents_Classifier-0.0.3.dist-info/WHEEL
Documents_Classifier-0.0.3.dist-info/top_level.txt
Documents_Classifier-0.0.3.dist-info/RECORD
