Metadata-Version: 2.1
Name: Documents-Classifier
Version: 0.0.3
Summary: A tool to classify images 
Author: Dang Thinh Hung, Trinh Nhu Phuong
Classifier: Programming Language :: Python :: 3.8
Classifier: Programming Language :: Python :: 3.9
Classifier: Programming Language :: Python :: 3.10
Classifier: License :: OSI Approved :: MIT License
Classifier: Operating System :: OS Independent
Requires-Python: <3.11.0,>=3.8.0
License-File: LICENSE
Requires-Dist: paddlepaddle ==2.5.1
Requires-Dist: paddleocr >=2.0.1
Requires-Dist: opencv-python
Requires-Dist: Pillow
Requires-Dist: numpy
Requires-Dist: nltk
Requires-Dist: transformers
Requires-Dist: torch
Requires-Dist: scikit-learn
Requires-Dist: scipy
Requires-Dist: threadpoolctl
Requires-Dist: pyyaml
Requires-Dist: packaging
Requires-Dist: huggingface-hub
Requires-Dist: tokenizers
Requires-Dist: safetensors
Requires-Dist: sentence-transformers
